README.md
setup.cfg
setup.py
comic_scraper/__init__.py
comic_scraper/base_comic.py
comic_scraper/comic_scraper.py
comic_scraper/current_comic.py
comic_scraper.egg-info/PKG-INFO
comic_scraper.egg-info/SOURCES.txt
comic_scraper.egg-info/dependency_links.txt
comic_scraper.egg-info/entry_points.txt
comic_scraper.egg-info/not-zip-safe
comic_scraper.egg-info/requires.txt
comic_scraper.egg-info/top_level.txt