Metadata-Version: 1.1
Name: comic-scraper
Version: 0.9.0
Summary: Scraps comics,mangas and creates cbz (/pdf) files for offline reading
Home-page: https://github.com/AbstractGeek/comic-scraper
Author: Dinesh Natesan
Author-email: abstractgeek@outlook.com
License: MIT
Download-URL: https://github.com/AbstractGeek/comic-scraper/tarball/0.9.0
Keywords: comics manga scraper
Platform: UNKNOWN
Classifier: Development Status :: 3 - Alpha
Classifier: License :: OSI Approved :: MIT License
Classifier: Programming Language :: Python :: 3.5
Classifier: Topic :: Games/Entertainment
